everysk_orjson-3.11.3.dist-info/METADATA
everysk_orjson-3.11.3.dist-info/WHEEL
everysk_orjson-3.11.3.dist-info/licenses/LICENSE-APACHE
everysk_orjson-3.11.3.dist-info/licenses/LICENSE-MIT
orjson/__init__.py
orjson/__init__.pyi
orjson/orjson.cpython-39-arm-linux-gnueabihf.so
orjson/py.typed
everysk_orjson-3.11.3.dist-info/RECORD
