Metadata-Version: 2.4
Name: everysk-orjson
Version: 3.11.3
Classifier: Development Status :: 5 - Production/Stable
Classifier: Intended Audience :: Developers
Classifier: License :: OSI Approved :: Apache Software License
Classifier: License :: OSI Approved :: MIT License
Classifier: Operating System :: MacOS
Classifier: Operating System :: Microsoft :: Windows
Classifier: Operating System :: POSIX :: Linux
Classifier: Programming Language :: Python :: 3
Classifier: Programming Language :: Python :: 3.9
Classifier: Programming Language :: Python :: 3.10
Classifier: Programming Language :: Python :: 3.11
Classifier: Programming Language :: Python :: 3.12
Classifier: Programming Language :: Python :: 3.13
Classifier: Programming Language :: Python :: 3.14
Classifier: Programming Language :: Python :: Implementation :: CPython
Classifier: Programming Language :: Python
Classifier: Programming Language :: Rust
Classifier: Typing :: Typed
License-File: LICENSE-APACHE
License-File: LICENSE-MIT
Summary: Fast, correct Python JSON library supporting dataclasses, datetimes, numpy, big integers, and special floating-point values.
Keywords: fast,json,dataclass,dataclasses,datetime,rfc,8259,3339
Author: Everysk Support <support@everysk.com>
Author-email: Everysk Support <support@everysk.com>
License: Apache-2.0 OR MIT
Requires-Python: >=3.9
Project-URL: source, https://github.com/Everysk/orjson
Project-URL: documentation, https://github.com/Everysk/orjson
Project-URL: changelog, https://github.com/Everysk/orjson/blob/master/CHANGELOG.md
